{
    "1.5.15": {
        "healthy": true,
        "supported": true,
        "healthy_error": null,
        "location": "/__w/apps/apps/trains/stable/diskoverdata/1.5.15",
        "last_update": "2025-09-03 12:56:43",
        "required_features": [],
        "human_version": "2.3.2_1.5.15",
        "version": "1.5.15",
        "app_metadata": {
            "annotations": {
                "min_scale_version": "24.10.2.2"
            },
            "app_version": "2.3.2",
            "capabilities": [
                {
                    "description": "Diskover Data is able to change file ownership arbitrarily",
                    "name": "CHOWN"
                },
                {
                    "description": "Diskover Data is able to bypass file permission checks",
                    "name": "DAC_OVERRIDE"
                },
                {
                    "description": "Diskover Data is able to bypass permission checks for file operations",
                    "name": "FOWNER"
                },
                {
                    "description": "Diskover Data is able to bind to privileged ports (< 1024)",
                    "name": "NET_BIND_SERVICE"
                },
                {
                    "description": "Diskover Data is able to change group ID of processes",
                    "name": "SETGID"
                },
                {
                    "description": "Diskover Data is able to change user ID of processes",
                    "name": "SETUID"
                }
            ],
            "categories": [
                "monitoring"
            ],
            "changelog_url": "https://docs.diskoverdata.com/diskover_changelogs/",
            "date_added": "2024-08-29",
            "description": "Diskover is used to monitor size/volumes of distributed dataset.",
            "home": "https://github.com/diskoverdata/diskover-community",
            "host_mounts": [],
            "icon": "https://media.sys.truenas.net/apps/diskoverdata/icons/icon.png",
            "keywords": [
                "storage",
                "monitoring",
                "management",
                "discovery"
            ],
            "lib_version": "2.1.49",
            "lib_version_hash": "e71e6b0122c9446fa5ea6fb07e7eb01b11fb42d549a19845426bbd7e21a42634",
            "maintainers": [
                {
                    "email": "dev@ixsystems.com",
                    "name": "truenas",
                    "url": "https://www.truenas.com/"
                }
            ],
            "name": "diskoverdata",
            "run_as_context": [
                {
                    "description": "Diskover runs as root user.",
                    "gid": 0,
                    "group_name": "root",
                    "uid": 0,
                    "user_name": "root"
                },
                {
                    "description": "Elastic Search runs as a non-root user.",
                    "gid": 1000,
                    "group_name": "elastic-search",
                    "uid": 1000,
                    "user_name": "elastic-search"
                }
            ],
            "screenshots": [
                "https://media.sys.truenas.net/apps/diskoverdata/screenshots/screenshot1.png",
                "https://media.sys.truenas.net/apps/diskoverdata/screenshots/screenshot2.png",
                "https://media.sys.truenas.net/apps/diskoverdata/screenshots/screenshot3.png"
            ],
            "sources": [
                "https://github.com/diskoverdata/diskover-community",
                "https://github.com/linuxserver/docker-diskover"
            ],
            "title": "Diskover Data",
            "train": "stable",
            "version": "1.5.15"
        },
        "schema": {
            "groups": [
                {
                    "name": "Diskover Data Configuration",
                    "description": "Configure Diskover Data"
                },
                {
                    "name": "User and Group Configuration",
                    "description": "Configure User and Group for Diskover Data"
                },
                {
                    "name": "Network Configuration",
                    "description": "Configure Network for Diskover Data"
                },
                {
                    "name": "Storage Configuration",
                    "description": "Configure Storage for Diskover Data"
                },
                {
                    "name": "Labels Configuration",
                    "description": "Configure Labels for Collabora"
                },
                {
                    "name": "Resources Configuration",
                    "description": "Configure Resources for Diskover Data"
                }
            ],
            "questions": [
                {
                    "variable": "TZ",
                    "group": "Diskover Data Configuration",
                    "label": "Timezone",
                    "schema": {
                        "type": "string",
                        "default": "Etc/UTC",
                        "required": true,
                        "$ref": [
                            "definitions/timezone"
                        ]
                    }
                },
                {
                    "variable": "diskover_data",
                    "label": "",
                    "group": "Diskover Data Configuration",
                    "schema": {
                        "type": "dict",
                        "attrs": [
                            {
                                "variable": "cron_schedule",
                                "label": "Cron Schedule",
                                "description": "The cron schedule for indexing data. </br>\nUntil the first run, the diskover data will display an error page.\n",
                                "schema": {
                                    "type": "string",
                                    "default": "*/15 * * * *",
                                    "required": true
                                }
                            },
                            {
                                "variable": "additional_envs",
                                "label": "Additional Environment Variables",
                                "schema": {
                                    "type": "list",
                                    "default": [],
                                    "items": [
                                        {
                                            "variable": "env",
                                            "label": "Environment Variable",
                                            "schema": {
                                                "type": "dict",
                                                "attrs": [
                                                    {
                                                        "variable": "name",
                                                        "label": "Name",
                                                        "schema": {
                                                            "type": "string",
                                                            "required": true
                                                        }
                                                    },
                                                    {
                                                        "variable": "value",
                                                        "label": "Value",
                                                        "schema": {
                                                            "type": "string"
                                                        }
                                                    }
                                                ]
                                            }
                                        }
                                    ]
                                }
                            }
                        ]
                    }
                },
                {
                    "variable": "run_as",
                    "label": "",
                    "group": "User and Group Configuration",
                    "schema": {
                        "type": "dict",
                        "attrs": [
                            {
                                "variable": "user",
                                "label": "User ID",
                                "description": "The user id that Diskover Data files will be owned by.",
                                "schema": {
                                    "type": "int",
                                    "min": 568,
                                    "default": 568,
                                    "required": true
                                }
                            },
                            {
                                "variable": "group",
                                "label": "Group ID",
                                "description": "The group id that Diskover Data files will be owned by.",
                                "schema": {
                                    "type": "int",
                                    "min": 568,
                                    "default": 568,
                                    "required": true
                                }
                            }
                        ]
                    }
                },
                {
                    "variable": "network",
                    "label": "",
                    "group": "Network Configuration",
                    "schema": {
                        "type": "dict",
                        "attrs": [
                            {
                                "variable": "web_port",
                                "label": "WebUI Port",
                                "schema": {
                                    "type": "dict",
                                    "show_if": [
                                        [
                                            "host_network",
                                            "=",
                                            false
                                        ]
                                    ],
                                    "attrs": [
                                        {
                                            "variable": "bind_mode",
                                            "label": "Port Bind Mode",
                                            "description": "The port bind mode.</br>\n- Publish: The port will be published on the host for external access.</br>\n- Expose: The port will be exposed for inter-container communication.</br>\n- None: The port will not be exposed or published.</br>\nNote: If the Dockerfile defines an EXPOSE directive,\nthe port will still be exposed for inter-container communication regardless of this setting.\n",
                                            "schema": {
                                                "type": "string",
                                                "default": "published",
                                                "enum": [
                                                    {
                                                        "value": "published",
                                                        "description": "Publish port on the host for external access"
                                                    },
                                                    {
                                                        "value": "exposed",
                                                        "description": "Expose port for inter-container communication"
                                                    },
                                                    {
                                                        "value": "",
                                                        "description": "None"
                                                    }
                                                ]
                                            }
                                        },
                                        {
                                            "variable": "port_number",
                                            "label": "Port Number",
                                            "schema": {
                                                "type": "int",
                                                "show_if": [
                                                    [
                                                        "bind_mode",
                                                        "=",
                                                        "published"
                                                    ]
                                                ],
                                                "default": 30102,
                                                "min": 1,
                                                "max": 65535,
                                                "required": true
                                            }
                                        },
                                        {
                                            "variable": "host_ips",
                                            "label": "Host IPs",
                                            "description": "IPs on the host to bind this port",
                                            "schema": {
                                                "type": "list",
                                                "show_if": [
                                                    [
                                                        "bind_mode",
                                                        "=",
                                                        "published"
                                                    ]
                                                ],
                                                "default": [],
                                                "items": [
                                                    {
                                                        "variable": "host_ip",
                                                        "label": "Host IP",
                                                        "schema": {
                                                            "type": "string",
                                                            "required": true,
                                                            "$ref": [
                                                                "definitions/node_bind_ip"
                                                            ]
                                                        }
                                                    }
                                                ]
                                            }
                                        }
                                    ]
                                }
                            },
                            {
                                "variable": "host_network",
                                "label": "Host Network",
                                "description": "Bind to the host network. It's recommended to keep this disabled.\n",
                                "schema": {
                                    "type": "boolean",
                                    "default": false
                                }
                            },
                            {
                                "variable": "dns_opts",
                                "label": "DNS Options",
                                "description": "DNS options for the container.</br>\nFormat: key:value</br>\nExample: attempts:3\n",
                                "schema": {
                                    "type": "list",
                                    "default": [],
                                    "items": [
                                        {
                                            "variable": "option",
                                            "label": "Option",
                                            "schema": {
                                                "type": "string",
                                                "required": true
                                            }
                                        }
                                    ]
                                }
                            }
                        ]
                    }
                },
                {
                    "variable": "storage",
                    "label": "",
                    "group": "Storage Configuration",
                    "schema": {
                        "type": "dict",
                        "attrs": [
                            {
                                "variable": "config",
                                "label": "Diskover Data Config Storage",
                                "description": "The path to store Diskover Data Config.",
                                "schema": {
                                    "type": "dict",
                                    "attrs": [
                                        {
                                            "variable": "type",
                                            "label": "Type",
                                            "description": "ixVolume: Is dataset created automatically by the system.</br>\nHost Path: Is a path that already exists on the system.\n",
                                            "schema": {
                                                "type": "string",
                                                "required": true,
                                                "default": "ix_volume",
                                                "enum": [
                                                    {
                                                        "value": "host_path",
                                                        "description": "Host Path (Path that already exists on the system)"
                                                    },
                                                    {
                                                        "value": "ix_volume",
                                                        "description": "ixVolume (Dataset created automatically by the system)"
                                                    }
                                                ]
                                            }
                                        },
                                        {
                                            "variable": "ix_volume_config",
                                            "label": "ixVolume Configuration",
                                            "description": "The configuration for the ixVolume dataset.",
                                            "schema": {
                                                "type": "dict",
                                                "show_if": [
                                                    [
                                                        "type",
                                                        "=",
                                                        "ix_volume"
                                                    ]
                                                ],
                                                "$ref": [
                                                    "normalize/ix_volume"
                                                ],
                                                "attrs": [
                                                    {
                                                        "variable": "acl_enable",
                                                        "label": "Enable ACL",
                                                        "description": "Enable ACL for the storage.",
                                                        "schema": {
                                                            "type": "boolean",
                                                            "default": false
                                                        }
                                                    },
                                                    {
                                                        "variable": "dataset_name",
                                                        "label": "Dataset Name",
                                                        "description": "The name of the dataset to use for storage.",
                                                        "schema": {
                                                            "type": "string",
                                                            "required": true,
                                                            "hidden": true,
                                                            "default": "config"
                                                        }
                                                    },
                                                    {
                                                        "variable": "acl_entries",
                                                        "label": "ACL Configuration",
                                                        "schema": {
                                                            "type": "dict",
                                                            "show_if": [
                                                                [
                                                                    "acl_enable",
                                                                    "=",
                                                                    true
                                                                ]
                                                            ],
                                                            "attrs": []
                                                        }
                                                    }
                                                ]
                                            }
                                        },
                                        {
                                            "variable": "host_path_config",
                                            "label": "Host Path Configuration",
                                            "schema": {
                                                "type": "dict",
                                                "show_if": [
                                                    [
                                                        "type",
                                                        "=",
                                                        "host_path"
                                                    ]
                                                ],
                                                "attrs": [
                                                    {
                                                        "variable": "acl_enable",
                                                        "label": "Enable ACL",
                                                        "description": "Enable ACL for the storage.",
                                                        "schema": {
                                                            "type": "boolean",
                                                            "default": false
                                                        }
                                                    },
                                                    {
                                                        "variable": "acl",
                                                        "label": "ACL Configuration",
                                                        "schema": {
                                                            "type": "dict",
                                                            "show_if": [
                                                                [
                                                                    "acl_enable",
                                                                    "=",
                                                                    true
                                                                ]
                                                            ],
                                                            "attrs": [],
                                                            "$ref": [
                                                                "normalize/acl"
                                                            ]
                                                        }
                                                    },
                                                    {
                                                        "variable": "path",
                                                        "label": "Host Path",
                                                        "description": "The host path to use for storage.",
                                                        "schema": {
                                                            "type": "hostpath",
                                                            "show_if": [
                                                                [
                                                                    "acl_enable",
                                                                    "=",
                                                                    false
                                                                ]
                                                            ],
                                                            "required": true
                                                        }
                                                    }
                                                ]
                                            }
                                        }
                                    ]
                                }
                            },
                            {
                                "variable": "data",
                                "label": "Diskover Data Storage",
                                "description": "The path to store Diskover Data.",
                                "schema": {
                                    "type": "dict",
                                    "attrs": [
                                        {
                                            "variable": "type",
                                            "label": "Type",
                                            "description": "ixVolume: Is dataset created automatically by the system.</br>\nHost Path: Is a path that already exists on the system.\n",
                                            "schema": {
                                                "type": "string",
                                                "required": true,
                                                "default": "ix_volume",
                                                "enum": [
                                                    {
                                                        "value": "host_path",
                                                        "description": "Host Path (Path that already exists on the system)"
                                                    },
                                                    {
                                                        "value": "ix_volume",
                                                        "description": "ixVolume (Dataset created automatically by the system)"
                                                    }
                                                ]
                                            }
                                        },
                                        {
                                            "variable": "ix_volume_config",
                                            "label": "ixVolume Configuration",
                                            "description": "The configuration for the ixVolume dataset.",
                                            "schema": {
                                                "type": "dict",
                                                "show_if": [
                                                    [
                                                        "type",
                                                        "=",
                                                        "ix_volume"
                                                    ]
                                                ],
                                                "$ref": [
                                                    "normalize/ix_volume"
                                                ],
                                                "attrs": [
                                                    {
                                                        "variable": "acl_enable",
                                                        "label": "Enable ACL",
                                                        "description": "Enable ACL for the storage.",
                                                        "schema": {
                                                            "type": "boolean",
                                                            "default": false
                                                        }
                                                    },
                                                    {
                                                        "variable": "dataset_name",
                                                        "label": "Dataset Name",
                                                        "description": "The name of the dataset to use for storage.",
                                                        "schema": {
                                                            "type": "string",
                                                            "required": true,
                                                            "hidden": true,
                                                            "default": "data"
                                                        }
                                                    },
                                                    {
                                                        "variable": "acl_entries",
                                                        "label": "ACL Configuration",
                                                        "schema": {
                                                            "type": "dict",
                                                            "show_if": [
                                                                [
                                                                    "acl_enable",
                                                                    "=",
                                                                    true
                                                                ]
                                                            ],
                                                            "attrs": []
                                                        }
                                                    }
                                                ]
                                            }
                                        },
                                        {
                                            "variable": "host_path_config",
                                            "label": "Host Path Configuration",
                                            "schema": {
                                                "type": "dict",
                                                "show_if": [
                                                    [
                                                        "type",
                                                        "=",
                                                        "host_path"
                                                    ]
                                                ],
                                                "attrs": [
                                                    {
                                                        "variable": "acl_enable",
                                                        "label": "Enable ACL",
                                                        "description": "Enable ACL for the storage.",
                                                        "schema": {
                                                            "type": "boolean",
                                                            "default": false
                                                        }
                                                    },
                                                    {
                                                        "variable": "acl",
                                                        "label": "ACL Configuration",
                                                        "schema": {
                                                            "type": "dict",
                                                            "show_if": [
                                                                [
                                                                    "acl_enable",
                                                                    "=",
                                                                    true
                                                                ]
                                                            ],
                                                            "attrs": [],
                                                            "$ref": [
                                                                "normalize/acl"
                                                            ]
                                                        }
                                                    },
                                                    {
                                                        "variable": "path",
                                                        "label": "Host Path",
                                                        "description": "The host path to use for storage.",
                                                        "schema": {
                                                            "type": "hostpath",
                                                            "show_if": [
                                                                [
                                                                    "acl_enable",
                                                                    "=",
                                                                    false
                                                                ]
                                                            ],
                                                            "required": true
                                                        }
                                                    }
                                                ]
                                            }
                                        }
                                    ]
                                }
                            },
                            {
                                "variable": "es_data",
                                "label": "Elastic Search Data Storage",
                                "description": "The path to store Elastic Search Data.",
                                "schema": {
                                    "type": "dict",
                                    "attrs": [
                                        {
                                            "variable": "type",
                                            "label": "Type",
                                            "description": "ixVolume: Is dataset created automatically by the system.</br>\nHost Path: Is a path that already exists on the system.\n",
                                            "schema": {
                                                "type": "string",
                                                "required": true,
                                                "default": "ix_volume",
                                                "enum": [
                                                    {
                                                        "value": "host_path",
                                                        "description": "Host Path (Path that already exists on the system)"
                                                    },
                                                    {
                                                        "value": "ix_volume",
                                                        "description": "ixVolume (Dataset created automatically by the system)"
                                                    }
                                                ]
                                            }
                                        },
                                        {
                                            "variable": "ix_volume_config",
                                            "label": "ixVolume Configuration",
                                            "description": "The configuration for the ixVolume dataset.",
                                            "schema": {
                                                "type": "dict",
                                                "show_if": [
                                                    [
                                                        "type",
                                                        "=",
                                                        "ix_volume"
                                                    ]
                                                ],
                                                "$ref": [
                                                    "normalize/ix_volume"
                                                ],
                                                "attrs": [
                                                    {
                                                        "variable": "acl_enable",
                                                        "label": "Enable ACL",
                                                        "description": "Enable ACL for the storage.",
                                                        "schema": {
                                                            "type": "boolean",
                                                            "default": false
                                                        }
                                                    },
                                                    {
                                                        "variable": "dataset_name",
                                                        "label": "Dataset Name",
                                                        "description": "The name of the dataset to use for storage.",
                                                        "schema": {
                                                            "type": "string",
                                                            "required": true,
                                                            "hidden": true,
                                                            "default": "es_data"
                                                        }
                                                    },
                                                    {
                                                        "variable": "acl_entries",
                                                        "label": "ACL Configuration",
                                                        "schema": {
                                                            "type": "dict",
                                                            "show_if": [
                                                                [
                                                                    "acl_enable",
                                                                    "=",
                                                                    true
                                                                ]
                                                            ],
                                                            "attrs": []
                                                        }
                                                    }
                                                ]
                                            }
                                        },
                                        {
                                            "variable": "host_path_config",
                                            "label": "Host Path Configuration",
                                            "schema": {
                                                "type": "dict",
                                                "show_if": [
                                                    [
                                                        "type",
                                                        "=",
                                                        "host_path"
                                                    ]
                                                ],
                                                "attrs": [
                                                    {
                                                        "variable": "acl_enable",
                                                        "label": "Enable ACL",
                                                        "description": "Enable ACL for the storage.",
                                                        "schema": {
                                                            "type": "boolean",
                                                            "default": false
                                                        }
                                                    },
                                                    {
                                                        "variable": "acl",
                                                        "label": "ACL Configuration",
                                                        "schema": {
                                                            "type": "dict",
                                                            "show_if": [
                                                                [
                                                                    "acl_enable",
                                                                    "=",
                                                                    true
                                                                ]
                                                            ],
                                                            "attrs": [],
                                                            "$ref": [
                                                                "normalize/acl"
                                                            ]
                                                        }
                                                    },
                                                    {
                                                        "variable": "path",
                                                        "label": "Host Path",
                                                        "description": "The host path to use for storage.",
                                                        "schema": {
                                                            "type": "hostpath",
                                                            "show_if": [
                                                                [
                                                                    "acl_enable",
                                                                    "=",
                                                                    false
                                                                ]
                                                            ],
                                                            "required": true
                                                        }
                                                    }
                                                ]
                                            }
                                        }
                                    ]
                                }
                            },
                            {
                                "variable": "additional_storage",
                                "label": "Additional Storage",
                                "schema": {
                                    "type": "list",
                                    "default": [],
                                    "items": [
                                        {
                                            "variable": "storageEntry",
                                            "label": "Storage Entry",
                                            "schema": {
                                                "type": "dict",
                                                "attrs": [
                                                    {
                                                        "variable": "type",
                                                        "label": "Type",
                                                        "description": "ixVolume: Is dataset created automatically by the system.</br>\nHost Path: Is a path that already exists on the system.</br>\nSMB Share: Is a SMB share that is mounted to as a volume.\n",
                                                        "schema": {
                                                            "type": "string",
                                                            "required": true,
                                                            "default": "ix_volume",
                                                            "enum": [
                                                                {
                                                                    "value": "host_path",
                                                                    "description": "Host Path (Path that already exists on the system)"
                                                                },
                                                                {
                                                                    "value": "ix_volume",
                                                                    "description": "ixVolume (Dataset created automatically by the system)"
                                                                },
                                                                {
                                                                    "value": "cifs",
                                                                    "description": "SMB/CIFS Share (Mounts a volume to a SMB share)"
                                                                }
                                                            ]
                                                        }
                                                    },
                                                    {
                                                        "variable": "index_data",
                                                        "label": "Enable Diskover Data Indexing",
                                                        "description": "Enable Diskover Data Indexing.",
                                                        "schema": {
                                                            "type": "boolean",
                                                            "default": false
                                                        }
                                                    },
                                                    {
                                                        "variable": "read_only",
                                                        "label": "Read Only",
                                                        "description": "Mount the volume as read only.",
                                                        "schema": {
                                                            "type": "boolean",
                                                            "default": false
                                                        }
                                                    },
                                                    {
                                                        "variable": "mount_path",
                                                        "label": "Mount Path",
                                                        "description": "The path inside the container to mount the storage.",
                                                        "schema": {
                                                            "type": "path",
                                                            "required": true
                                                        }
                                                    },
                                                    {
                                                        "variable": "host_path_config",
                                                        "label": "Host Path Configuration",
                                                        "schema": {
                                                            "type": "dict",
                                                            "show_if": [
                                                                [
                                                                    "type",
                                                                    "=",
                                                                    "host_path"
                                                                ]
                                                            ],
                                                            "attrs": [
                                                                {
                                                                    "variable": "acl_enable",
                                                                    "label": "Enable ACL",
                                                                    "description": "Enable ACL for the storage.",
                                                                    "schema": {
                                                                        "type": "boolean",
                                                                        "default": false
                                                                    }
                                                                },
                                                                {
                                                                    "variable": "acl",
                                                                    "label": "ACL Configuration",
                                                                    "schema": {
                                                                        "type": "dict",
                                                                        "show_if": [
                                                                            [
                                                                                "acl_enable",
                                                                                "=",
                                                                                true
                                                                            ]
                                                                        ],
                                                                        "attrs": [],
                                                                        "$ref": [
                                                                            "normalize/acl"
                                                                        ]
                                                                    }
                                                                },
                                                                {
                                                                    "variable": "path",
                                                                    "label": "Host Path",
                                                                    "description": "The host path to use for storage.",
                                                                    "schema": {
                                                                        "type": "hostpath",
                                                                        "show_if": [
                                                                            [
                                                                                "acl_enable",
                                                                                "=",
                                                                                false
                                                                            ]
                                                                        ],
                                                                        "required": true
                                                                    }
                                                                }
                                                            ]
                                                        }
                                                    },
                                                    {
                                                        "variable": "ix_volume_config",
                                                        "label": "ixVolume Configuration",
                                                        "description": "The configuration for the ixVolume dataset.",
                                                        "schema": {
                                                            "type": "dict",
                                                            "show_if": [
                                                                [
                                                                    "type",
                                                                    "=",
                                                                    "ix_volume"
                                                                ]
                                                            ],
                                                            "$ref": [
                                                                "normalize/ix_volume"
                                                            ],
                                                            "attrs": [
                                                                {
                                                                    "variable": "acl_enable",
                                                                    "label": "Enable ACL",
                                                                    "description": "Enable ACL for the storage.",
                                                                    "schema": {
                                                                        "type": "boolean",
                                                                        "default": false
                                                                    }
                                                                },
                                                                {
                                                                    "variable": "dataset_name",
                                                                    "label": "Dataset Name",
                                                                    "description": "The name of the dataset to use for storage.",
                                                                    "schema": {
                                                                        "type": "string",
                                                                        "required": true,
                                                                        "default": "storage_entry"
                                                                    }
                                                                },
                                                                {
                                                                    "variable": "acl_entries",
                                                                    "label": "ACL Configuration",
                                                                    "schema": {
                                                                        "type": "dict",
                                                                        "show_if": [
                                                                            [
                                                                                "acl_enable",
                                                                                "=",
                                                                                true
                                                                            ]
                                                                        ],
                                                                        "attrs": [],
                                                                        "$ref": [
                                                                            "normalize/acl"
                                                                        ]
                                                                    }
                                                                }
                                                            ]
                                                        }
                                                    },
                                                    {
                                                        "variable": "cifs_config",
                                                        "label": "SMB Configuration",
                                                        "description": "The configuration for the SMB dataset.",
                                                        "schema": {
                                                            "type": "dict",
                                                            "show_if": [
                                                                [
                                                                    "type",
                                                                    "=",
                                                                    "cifs"
                                                                ]
                                                            ],
                                                            "attrs": [
                                                                {
                                                                    "variable": "server",
                                                                    "label": "Server",
                                                                    "description": "The server to mount the SMB share.",
                                                                    "schema": {
                                                                        "type": "string",
                                                                        "required": true
                                                                    }
                                                                },
                                                                {
                                                                    "variable": "path",
                                                                    "label": "Path",
                                                                    "description": "The path to mount the SMB share.",
                                                                    "schema": {
                                                                        "type": "string",
                                                                        "required": true
                                                                    }
                                                                },
                                                                {
                                                                    "variable": "username",
                                                                    "label": "Username",
                                                                    "description": "The username to use for the SMB share.",
                                                                    "schema": {
                                                                        "type": "string",
                                                                        "required": true
                                                                    }
                                                                },
                                                                {
                                                                    "variable": "password",
                                                                    "label": "Password",
                                                                    "description": "The password to use for the SMB share.",
                                                                    "schema": {
                                                                        "type": "string",
                                                                        "required": true,
                                                                        "private": true
                                                                    }
                                                                },
                                                                {
                                                                    "variable": "domain",
                                                                    "label": "Domain",
                                                                    "description": "The domain to use for the SMB share.",
                                                                    "schema": {
                                                                        "type": "string"
                                                                    }
                                                                }
                                                            ]
                                                        }
                                                    }
                                                ]
                                            }
                                        }
                                    ]
                                }
                            }
                        ]
                    }
                },
                {
                    "variable": "labels",
                    "label": "",
                    "group": "Labels Configuration",
                    "schema": {
                        "type": "list",
                        "default": [],
                        "items": [
                            {
                                "variable": "label",
                                "label": "Label",
                                "schema": {
                                    "type": "dict",
                                    "attrs": [
                                        {
                                            "variable": "key",
                                            "label": "Key",
                                            "schema": {
                                                "type": "string",
                                                "required": true
                                            }
                                        },
                                        {
                                            "variable": "value",
                                            "label": "Value",
                                            "schema": {
                                                "type": "string",
                                                "required": true
                                            }
                                        },
                                        {
                                            "variable": "containers",
                                            "label": "Containers",
                                            "description": "Containers where the label should be applied",
                                            "schema": {
                                                "type": "list",
                                                "items": [
                                                    {
                                                        "variable": "container",
                                                        "label": "Container",
                                                        "schema": {
                                                            "type": "string",
                                                            "required": true,
                                                            "enum": [
                                                                {
                                                                    "value": "diskoverdata",
                                                                    "description": "diskoverdata"
                                                                },
                                                                {
                                                                    "value": "elastic-search",
                                                                    "description": "elastic-search"
                                                                }
                                                            ]
                                                        }
                                                    }
                                                ]
                                            }
                                        }
                                    ]
                                }
                            }
                        ]
                    }
                },
                {
                    "variable": "resources",
                    "label": "",
                    "group": "Resources Configuration",
                    "schema": {
                        "type": "dict",
                        "attrs": [
                            {
                                "variable": "limits",
                                "label": "Limits",
                                "schema": {
                                    "type": "dict",
                                    "attrs": [
                                        {
                                            "variable": "cpus",
                                            "label": "CPUs",
                                            "description": "CPUs limit for Diskover Data.",
                                            "schema": {
                                                "type": "int",
                                                "default": 2,
                                                "required": true
                                            }
                                        },
                                        {
                                            "variable": "memory",
                                            "label": "Memory (in MB)",
                                            "description": "Memory limit for Diskover Data.",
                                            "schema": {
                                                "type": "int",
                                                "default": 4096,
                                                "required": true
                                            }
                                        }
                                    ]
                                }
                            }
                        ]
                    }
                }
            ]
        },
        "readme": "<h1>Diskover Data</h1> <p><a href=\"https://github.com/diskoverdata/diskover-community\">Diskover Data</a> is used to monitor size/volumes of distributed dataset.</p>",
        "changelog": null,
        "chart_metadata": {
            "annotations": {
                "min_scale_version": "24.10.2.2"
            },
            "app_version": "2.3.2",
            "capabilities": [
                {
                    "description": "Diskover Data is able to change file ownership arbitrarily",
                    "name": "CHOWN"
                },
                {
                    "description": "Diskover Data is able to bypass file permission checks",
                    "name": "DAC_OVERRIDE"
                },
                {
                    "description": "Diskover Data is able to bypass permission checks for file operations",
                    "name": "FOWNER"
                },
                {
                    "description": "Diskover Data is able to bind to privileged ports (< 1024)",
                    "name": "NET_BIND_SERVICE"
                },
                {
                    "description": "Diskover Data is able to change group ID of processes",
                    "name": "SETGID"
                },
                {
                    "description": "Diskover Data is able to change user ID of processes",
                    "name": "SETUID"
                }
            ],
            "categories": [
                "monitoring"
            ],
            "changelog_url": "https://docs.diskoverdata.com/diskover_changelogs/",
            "date_added": "2024-08-29",
            "description": "Diskover is used to monitor size/volumes of distributed dataset.",
            "home": "https://github.com/diskoverdata/diskover-community",
            "host_mounts": [],
            "icon": "https://media.sys.truenas.net/apps/diskoverdata/icons/icon.png",
            "keywords": [
                "storage",
                "monitoring",
                "management",
                "discovery"
            ],
            "lib_version": "2.1.49",
            "lib_version_hash": "e71e6b0122c9446fa5ea6fb07e7eb01b11fb42d549a19845426bbd7e21a42634",
            "maintainers": [
                {
                    "email": "dev@ixsystems.com",
                    "name": "truenas",
                    "url": "https://www.truenas.com/"
                }
            ],
            "name": "diskoverdata",
            "run_as_context": [
                {
                    "description": "Diskover runs as root user.",
                    "gid": 0,
                    "group_name": "root",
                    "uid": 0,
                    "user_name": "root"
                },
                {
                    "description": "Elastic Search runs as a non-root user.",
                    "gid": 1000,
                    "group_name": "elastic-search",
                    "uid": 1000,
                    "user_name": "elastic-search"
                }
            ],
            "screenshots": [
                "https://media.sys.truenas.net/apps/diskoverdata/screenshots/screenshot1.png",
                "https://media.sys.truenas.net/apps/diskoverdata/screenshots/screenshot2.png",
                "https://media.sys.truenas.net/apps/diskoverdata/screenshots/screenshot3.png"
            ],
            "sources": [
                "https://github.com/diskoverdata/diskover-community",
                "https://github.com/linuxserver/docker-diskover"
            ],
            "title": "Diskover Data",
            "train": "stable",
            "version": "1.5.15"
        }
    }
}